reos-0.1.0.dist-info/METADATA
reos-0.1.0.dist-info/WHEEL
reos/__init__.py
reos/reos.cpython-312-x86_64-linux-gnu.so
reos-0.1.0.dist-info/RECORD
