Metadata-Version: 2.4
Name: reos
Version: 0.1.0
Classifier: Programming Language :: Rust
Classifier: Programming Language :: Python :: Implementation :: CPython
Classifier: Programming Language :: Python :: Implementation :: PyPy
Summary: A Library for Thermodynamics using Cubic & Associative contributions written in Rust.
Author-email: Emanuel <emanuka@eq.ufrj.br>
Requires-Python: >=3.8
